{
    "Object": [
        {
            "Title": "afdian.net",
            "Subtitle": "赞助页面",
            "Type": "link",
            "Body": "https://afdian.net/@1059Studio"
        },
        {
            "Title": "Gitee 发布页",
            "Subtitle": "发布页",
            "Type": "link",
            "Body": "https://gitee.com/Lake1059/Lake1059.SMUI"
        },
        {
            "Title": "GitHub 发布页",
            "Subtitle": "发布页",
            "Type": "link",
            "Body": "https://github.com/Lake1059/Lake1059.SMUI"
        }
    ]
}